{
  "schemaVersion": 1,
  "id": "oneblockswimming",
  "version": "${version}",
  "name": "One Block Swimming",
  "description": "A Server-side mod that allows players to start swimming in one block of water.",
  "authors": ["S-N00B-1"],
  "contact": {
    "homepage": "https://modrinth.com/mod/oneBlockSwimming/",
    "issues": "https://github.com/S-N00B-1/oneBlockSwimming/issues",
    "sources": "https://github.com/S-N00B-1/oneBlockSwimming"
  },
  "license": "MIT",
  "icon": "assets/oneblockswimming/icon.png",
  "environment": "*",
  "mixins": [
    "oneblockswimming.mixins.json"
  ],
  "depends": {
    "fabricloader": "*",
    "minecraft": ">=${minecraft_version}"
  }
}
